quickbot/__init__.py
quickbot/main.py
quickbot/plugin.py
quickbot/router.py
quickbot/api_route/depends.py
quickbot/api_route/models.py
quickbot/api_route/telegram.py
quickbot/auth/__init__.py
quickbot/auth/jwt.py
quickbot/auth/telegram.py
quickbot/bot/command_context_filter.py
quickbot/bot/handlers/__init__.py
quickbot/bot/handlers/context.py
quickbot/bot/handlers/start.py
quickbot/bot/handlers/common/filtering.py
quickbot/bot/handlers/common/filtering_callbacks.py
quickbot/bot/handlers/common/pagination.py
quickbot/bot/handlers/common/routing.py
quickbot/bot/handlers/editors/boolean.py
quickbot/bot/handlers/editors/common.py
quickbot/bot/handlers/editors/date.py
quickbot/bot/handlers/editors/entity.py
quickbot/bot/handlers/editors/main.py
quickbot/bot/handlers/editors/main_callbacks.py
quickbot/bot/handlers/editors/string.py
quickbot/bot/handlers/editors/wrapper.py
quickbot/bot/handlers/forms/entity_form.py
quickbot/bot/handlers/forms/entity_form_callbacks.py
quickbot/bot/handlers/forms/entity_list.py
quickbot/bot/handlers/menu/entities.py
quickbot/bot/handlers/menu/language.py
quickbot/bot/handlers/menu/main.py
quickbot/bot/handlers/menu/parameters.py
quickbot/bot/handlers/menu/settings.py
quickbot/bot/handlers/user_handlers/command_handler.py
quickbot/bot/handlers/user_handlers/main.py
quickbot/config/__init__.py
quickbot/db/__init__.py
quickbot/fsm/db_storage.py
quickbot/helpers/__init__.py
quickbot/middleware/telegram/__init__.py
quickbot/middleware/telegram/auth.py
quickbot/middleware/telegram/i18n.py
quickbot/middleware/telegram/reset_state.py
quickbot/model/__init__.py
quickbot/model/_singleton.py
quickbot/model/annotated_schema.py
quickbot/model/bot_entity.py
quickbot/model/bot_enum.py
quickbot/model/bot_metadata.py
quickbot/model/bot_process.py
quickbot/model/crud_command.py
quickbot/model/crud_service.py
quickbot/model/default_user.py
quickbot/model/descriptors.py
quickbot/model/fsm_storage.py
quickbot/model/language.py
quickbot/model/list_schema.py
quickbot-0.1.1.dist-info/licenses/LICENSE
quickbot-0.1.1.dist-info/METADATA
quickbot-0.1.1.dist-info/WHEEL
quickbot-0.1.1.dist-info/top_level.txt
quickbot-0.1.1.dist-info/RECORD
