Metadata-Version: 2.4
Name: quickbot
Version: 0.1.1
Summary: quickbot - Rapid Application Development Framework for Telegram Bots
Author-email: Alexander Kalinovsky <ak@botforge.biz>
License: MIT License
Classifier: Programming Language :: Python :: 3
Classifier: Operating System :: OS Independent
Classifier: Development Status :: 3 - Alpha
Requires-Python: >=3.13
License-File: LICENSE
Requires-Dist: aiogram>=3.17.0
Requires-Dist: asyncpg>=0.30.0
Requires-Dist: fastapi[standard]>=0.115.8
Requires-Dist: greenlet>=3.1.1
Requires-Dist: pydantic-settings>=2.7.1
Requires-Dist: sqlmodel>=0.0.24
Requires-Dist: ujson>=5.10.0
Provides-Extra: i18n
Requires-Dist: aiogram[i18n]>=3.17.0; extra == "i18n"
Requires-Dist: babel>=2.17.0; extra == "i18n"
Provides-Extra: dev
Requires-Dist: build>=1.2.1; extra == "dev"
Requires-Dist: twine>=5.0.0; extra == "dev"
Requires-Dist: pytest>=8.0.0; extra == "dev"
Requires-Dist: ruff>=0.5.0; extra == "dev"
Dynamic: license-file
